second_opinion_ruler/__init__.py
second_opinion_ruler/main.py
second_opinion_ruler-0.1.0.dist-info/entry_points.txt
second_opinion_ruler-0.1.0.dist-info/LICENSE
second_opinion_ruler-0.1.0.dist-info/WHEEL
second_opinion_ruler-0.1.0.dist-info/METADATA
second_opinion_ruler-0.1.0.dist-info/RECORD
