Metadata-Version: 2.1
Name: second-opinion-ruler
Version: 0.1.0
Summary: A spaCy custom component that extends the SpanRuler with a second opinion
Home-page: https://github.com/mr-bjerre/second-opinion-ruler
License: MIT
Keywords: python,spaCy,custom component
Author: Nicolai Bjerre Pedersen
Maintainer: Nicolai Bjerre Pedersen
Requires-Python: >=3.10,<4.0
Classifier: Development Status :: 4 - Beta
Classifier: Environment :: Console
Classifier: Environment :: MacOS X
Classifier: Intended Audience :: Developers
Classifier: Intended Audience :: Education
Classifier: Intended Audience :: Information Technology
Classifier: Intended Audience :: Science/Research
Classifier: License :: OSI Approved :: MIT License
Classifier: Operating System :: POSIX :: Linux
Classifier: Operating System :: Unix
Classifier: Programming Language :: Python :: 3
Classifier: Programming Language :: Python :: 3.10
Classifier: Programming Language :: Python :: 3 :: Only
Classifier: Programming Language :: Python :: 3.10
Classifier: Topic :: Scientific/Engineering
Classifier: Topic :: Scientific/Engineering :: Artificial Intelligence
Classifier: Topic :: Scientific/Engineering :: Information Analysis
Classifier: Topic :: Software Development
Classifier: Topic :: Software Development :: Libraries
Classifier: Topic :: Software Development :: Libraries :: Python Modules
Requires-Dist: spacy (>=3.4.1,<4.0.0); sys_platform != "darwin"
Requires-Dist: spacy[apple] (>=3.4.1,<4.0.0); sys_platform == "darwin"
Project-URL: Documentation, https://github.com/mr-bjerre/second-opinion-ruler#readme
Project-URL: Repository, https://github.com/mr-bjerre/second-opinion-ruler
